{
  "id": "AZ508035",
  "level": 2,
  "level_name": {
    "local": "Yaşayış məntəqəsi",
    "en": "Settlement"
  },
  "name": {
    "local": "Firuzabad",
    "en": "Firuzabad",
    "slug": "firuzabad"
  },
  "code": {
    "id": "AZ508035",
    "iso": null
  },
  "parent": {
    "id": "AZ508",
    "level": 1,
    "name": {
      "local": "Göygöl",
      "en": "Goygol",
      "slug": "goygol"
    }
  },
  "ancestors": [
    {
      "id": "AZ508",
      "level": 1,
      "name": {
        "local": "Göygöl",
        "en": "Goygol",
        "slug": "goygol"
      }
    }
  ],
  "children_count": {},
  "zip_codes": [],
  "geo": {
    "lat": "40.61",
    "lon": "46.312"
  },
  "metadata": {},
  "source": {}
}