{
  "id": "AZ410050",
  "level": 2,
  "level_name": {
    "local": "Yaşayış məntəqəsi",
    "en": "Settlement"
  },
  "name": {
    "local": "Əhmədli",
    "en": "Ahmadli",
    "slug": "ahmadli"
  },
  "code": {
    "id": "AZ410050",
    "iso": null
  },
  "parent": {
    "id": "AZ410",
    "level": 1,
    "name": {
      "local": "Şamaxı",
      "en": "Shamakhi",
      "slug": "shamakhi"
    }
  },
  "ancestors": [
    {
      "id": "AZ410",
      "level": 1,
      "name": {
        "local": "Şamaxı",
        "en": "Shamakhi",
        "slug": "shamakhi"
      }
    }
  ],
  "children_count": {},
  "zip_codes": [],
  "geo": {
    "lat": "40.737",
    "lon": "48.701"
  },
  "metadata": {},
  "source": {}
}