{
  "id": "AZ901035",
  "level": 2,
  "level_name": {
    "local": "Yaşayış məntəqəsi",
    "en": "Settlement"
  },
  "name": {
    "local": "Qaraoğlan",
    "en": "Garaoghlan",
    "slug": "garaoghlan"
  },
  "code": {
    "id": "AZ901035",
    "iso": null
  },
  "parent": {
    "id": "AZ901",
    "level": 1,
    "name": {
      "local": "Yevlax",
      "en": "Yevlakh",
      "slug": "yevlakh"
    }
  },
  "ancestors": [
    {
      "id": "AZ901",
      "level": 1,
      "name": {
        "local": "Yevlax",
        "en": "Yevlakh",
        "slug": "yevlakh"
      }
    }
  ],
  "children_count": {},
  "zip_codes": [],
  "geo": {
    "lat": "40.658",
    "lon": "47.189"
  },
  "metadata": {},
  "source": {}
}