{
  "id": "AZ604079",
  "level": 2,
  "level_name": {
    "local": "Yaşayış məntəqəsi",
    "en": "Settlement"
  },
  "name": {
    "local": "Mincivan",
    "en": "Minjivan",
    "slug": "minjivan"
  },
  "code": {
    "id": "AZ604079",
    "iso": null
  },
  "parent": {
    "id": "AZ604",
    "level": 1,
    "name": {
      "local": "Zəngilan",
      "en": "Zangilan",
      "slug": "zangilan"
    }
  },
  "ancestors": [
    {
      "id": "AZ604",
      "level": 1,
      "name": {
        "local": "Zəngilan",
        "en": "Zangilan",
        "slug": "zangilan"
      }
    }
  ],
  "children_count": {},
  "zip_codes": [],
  "geo": {
    "lat": "39.03",
    "lon": "46.722"
  },
  "metadata": {},
  "source": {}
}