{
  "id": "AZ107018",
  "level": 2,
  "level_name": {
    "local": "Yaşayış məntəqəsi",
    "en": "Settlement"
  },
  "name": {
    "local": "Nürgüt",
    "en": "Nurgut",
    "slug": "nurgut"
  },
  "code": {
    "id": "AZ107018",
    "iso": null
  },
  "parent": {
    "id": "AZ107",
    "level": 1,
    "name": {
      "local": "Ordubad",
      "en": "Ordubad",
      "slug": "ordubad"
    }
  },
  "ancestors": [
    {
      "id": "AZ107",
      "level": 1,
      "name": {
        "local": "Ordubad",
        "en": "Ordubad",
        "slug": "ordubad"
      }
    }
  ],
  "children_count": {},
  "zip_codes": [],
  "geo": {
    "lat": "39.223",
    "lon": "45.9"
  },
  "metadata": {},
  "source": {}
}