{
  "id": "AZ301046",
  "level": 2,
  "level_name": {
    "local": "Yaşayış məntəqəsi",
    "en": "Settlement"
  },
  "name": {
    "local": "Aşağı Qələnxur",
    "en": "Ashaghi Galankhur",
    "slug": "ashaghi-galankhur"
  },
  "code": {
    "id": "AZ301046",
    "iso": null
  },
  "parent": {
    "id": "AZ301",
    "level": 1,
    "name": {
      "local": "Qusar",
      "en": "Gusar",
      "slug": "gusar"
    }
  },
  "ancestors": [
    {
      "id": "AZ301",
      "level": 1,
      "name": {
        "local": "Qusar",
        "en": "Gusar",
        "slug": "gusar"
      }
    }
  ],
  "children_count": {},
  "zip_codes": [],
  "geo": {
    "lat": "41.499",
    "lon": "48.151"
  },
  "metadata": {},
  "source": {}
}