{
  "id": "AZ2001004",
  "level": 2,
  "level_name": {
    "local": "Yaşayış məntəqəsi",
    "en": "Settlement"
  },
  "name": {
    "local": "Şıxzamanlı",
    "en": "Shikhzamanli",
    "slug": "shikhzamanli"
  },
  "code": {
    "id": "AZ2001004",
    "iso": null
  },
  "parent": {
    "id": "AZ2001",
    "level": 1,
    "name": {
      "local": "Gəncə",
      "en": "Ganja",
      "slug": "ganja"
    }
  },
  "ancestors": [
    {
      "id": "AZ2001",
      "level": 1,
      "name": {
        "local": "Gəncə",
        "en": "Ganja",
        "slug": "ganja"
      }
    }
  ],
  "children_count": {},
  "zip_codes": [],
  "geo": {
    "lat": "40.718",
    "lon": "46.376"
  },
  "metadata": {},
  "source": {}
}