{
  "id": "AZ606027",
  "level": 2,
  "level_name": {
    "local": "Yaşayış məntəqəsi",
    "en": "Settlement"
  },
  "name": {
    "local": "Qarğabazar",
    "en": "Garghabazar",
    "slug": "garghabazar"
  },
  "code": {
    "id": "AZ606027",
    "iso": null
  },
  "parent": {
    "id": "AZ606",
    "level": 1,
    "name": {
      "local": "Füzuli",
      "en": "Fuzuli",
      "slug": "fuzuli"
    }
  },
  "ancestors": [
    {
      "id": "AZ606",
      "level": 1,
      "name": {
        "local": "Füzuli",
        "en": "Fuzuli",
        "slug": "fuzuli"
      }
    }
  ],
  "children_count": {},
  "zip_codes": [],
  "geo": {
    "lat": "39.54",
    "lon": "47.158"
  },
  "metadata": {},
  "source": {}
}