{
  "id": "AZ407055",
  "level": 2,
  "level_name": {
    "local": "Yaşayış məntəqəsi",
    "en": "Settlement"
  },
  "name": {
    "local": "Zeyvə",
    "en": "Zeyva",
    "slug": "zeyva"
  },
  "code": {
    "id": "AZ407055",
    "iso": null
  },
  "parent": {
    "id": "AZ407",
    "level": 1,
    "name": {
      "local": "İsmayıllı",
      "en": "Ismayilli",
      "slug": "ismayilli"
    }
  },
  "ancestors": [
    {
      "id": "AZ407",
      "level": 1,
      "name": {
        "local": "İsmayıllı",
        "en": "Ismayilli",
        "slug": "ismayilli"
      }
    }
  ],
  "children_count": {},
  "zip_codes": [],
  "geo": {
    "lat": "40.752",
    "lon": "48.399"
  },
  "metadata": {},
  "source": {}
}