{
  "id": "AZ802044",
  "level": 2,
  "level_name": {
    "local": "Yaşayış məntəqəsi",
    "en": "Settlement"
  },
  "name": {
    "local": "Kosalar",
    "en": "Kosalar",
    "slug": "kosalar"
  },
  "code": {
    "id": "AZ802044",
    "iso": null
  },
  "parent": {
    "id": "AZ802",
    "level": 1,
    "name": {
      "local": "Lənkəran",
      "en": "Lankaran",
      "slug": "lankaran"
    }
  },
  "ancestors": [
    {
      "id": "AZ802",
      "level": 1,
      "name": {
        "local": "Lənkəran",
        "en": "Lankaran",
        "slug": "lankaran"
      }
    }
  ],
  "children_count": {},
  "zip_codes": [],
  "geo": {
    "lat": "38.708",
    "lon": "48.809"
  },
  "metadata": {},
  "source": {}
}