{
  "id": "AZ401051",
  "level": 2,
  "level_name": {
    "local": "Yaşayış məntəqəsi",
    "en": "Settlement"
  },
  "name": {
    "local": "Yeni Şərif",
    "en": "Yeni Sharif",
    "slug": "yeni-sharif"
  },
  "code": {
    "id": "AZ401051",
    "iso": null
  },
  "parent": {
    "id": "AZ401",
    "level": 1,
    "name": {
      "local": "Balakən",
      "en": "Balakan",
      "slug": "balakan"
    }
  },
  "ancestors": [
    {
      "id": "AZ401",
      "level": 1,
      "name": {
        "local": "Balakən",
        "en": "Balakan",
        "slug": "balakan"
      }
    }
  ],
  "children_count": {},
  "zip_codes": [],
  "geo": {
    "lat": "41.745",
    "lon": "46.267"
  },
  "metadata": {},
  "source": {}
}