{
  "id": "AZ509003",
  "level": 2,
  "level_name": {
    "local": "Yaşayış məntəqəsi",
    "en": "Settlement"
  },
  "name": {
    "local": "Dəliməmmədli",
    "en": "DALIMAMMADLI",
    "slug": "dalimammadli"
  },
  "code": {
    "id": "AZ509003",
    "iso": null
  },
  "parent": {
    "id": "AZ509",
    "level": 1,
    "name": {
      "local": "Goranboy",
      "en": "Goranboy",
      "slug": "goranboy"
    }
  },
  "ancestors": [
    {
      "id": "AZ509",
      "level": 1,
      "name": {
        "local": "Goranboy",
        "en": "Goranboy",
        "slug": "goranboy"
      }
    }
  ],
  "children_count": {},
  "zip_codes": [],
  "geo": {
    "lat": "40.695",
    "lon": "46.571"
  },
  "metadata": {},
  "source": {}
}