{
  "id": "AZ607032",
  "level": 2,
  "level_name": {
    "local": "Yaşayış məntəqəsi",
    "en": "Settlement"
  },
  "name": {
    "local": "Mil",
    "en": "Mil",
    "slug": "mil"
  },
  "code": {
    "id": "AZ607032",
    "iso": null
  },
  "parent": {
    "id": "AZ607",
    "level": 1,
    "name": {
      "local": "Beyləqan",
      "en": "Beylagan",
      "slug": "beylagan"
    }
  },
  "ancestors": [
    {
      "id": "AZ607",
      "level": 1,
      "name": {
        "local": "Beyləqan",
        "en": "Beylagan",
        "slug": "beylagan"
      }
    }
  ],
  "children_count": {},
  "zip_codes": [],
  "geo": {
    "lat": "39.638",
    "lon": "47.686"
  },
  "metadata": {},
  "source": {}
}