{
  "id": "AZ602097",
  "level": 2,
  "level_name": {
    "local": "Yaşayış məntəqəsi",
    "en": "Settlement"
  },
  "name": {
    "local": "Qaraçanlı",
    "en": "Garachanli",
    "slug": "garachanli"
  },
  "code": {
    "id": "AZ602097",
    "iso": null
  },
  "parent": {
    "id": "AZ602",
    "level": 1,
    "name": {
      "local": "Laçın",
      "en": "Lachin",
      "slug": "lachin"
    }
  },
  "ancestors": [
    {
      "id": "AZ602",
      "level": 1,
      "name": {
        "local": "Laçın",
        "en": "Lachin",
        "slug": "lachin"
      }
    }
  ],
  "children_count": {},
  "zip_codes": [],
  "geo": {
    "lat": "39.74",
    "lon": "46.391"
  },
  "metadata": {},
  "source": {}
}