{
  "id": "AZ406011",
  "level": 2,
  "level_name": {
    "local": "Yaşayış məntəqəsi",
    "en": "Settlement"
  },
  "name": {
    "local": "Bəyli",
    "en": "Beyli",
    "slug": "beyli"
  },
  "code": {
    "id": "AZ406011",
    "iso": null
  },
  "parent": {
    "id": "AZ406",
    "level": 1,
    "name": {
      "local": "Qəbələ",
      "en": "Gabala",
      "slug": "gabala"
    }
  },
  "ancestors": [
    {
      "id": "AZ406",
      "level": 1,
      "name": {
        "local": "Qəbələ",
        "en": "Gabala",
        "slug": "gabala"
      }
    }
  ],
  "children_count": {},
  "zip_codes": [],
  "geo": {
    "lat": "40.816",
    "lon": "47.613"
  },
  "metadata": {},
  "source": {}
}