{
  "id": "AZ105021",
  "level": 2,
  "level_name": {
    "local": "Yaşayış məntəqəsi",
    "en": "Settlement"
  },
  "name": {
    "local": "Ağbulaq",
    "en": "Aghbulag",
    "slug": "aghbulag"
  },
  "code": {
    "id": "AZ105021",
    "iso": null
  },
  "parent": {
    "id": "AZ105",
    "level": 1,
    "name": {
      "local": "Şahbuz",
      "en": "Shahbuz",
      "slug": "shahbuz"
    }
  },
  "ancestors": [
    {
      "id": "AZ105",
      "level": 1,
      "name": {
        "local": "Şahbuz",
        "en": "Shahbuz",
        "slug": "shahbuz"
      }
    }
  ],
  "children_count": {},
  "zip_codes": [],
  "geo": {
    "lat": "39.447",
    "lon": "45.721"
  },
  "metadata": {},
  "source": {}
}