{
  "id": "AZ102042",
  "level": 2,
  "level_name": {
    "local": "Yaşayış məntəqəsi",
    "en": "Settlement"
  },
  "name": {
    "local": "Yuxarı Aralıq",
    "en": "Yukhari Aralig",
    "slug": "yukhari-aralig"
  },
  "code": {
    "id": "AZ102042",
    "iso": null
  },
  "parent": {
    "id": "AZ102",
    "level": 1,
    "name": {
      "local": "Şərur",
      "en": "Sharur",
      "slug": "sharur"
    }
  },
  "ancestors": [
    {
      "id": "AZ102",
      "level": 1,
      "name": {
        "local": "Şərur",
        "en": "Sharur",
        "slug": "sharur"
      }
    }
  ],
  "children_count": {},
  "zip_codes": [],
  "geo": {
    "lat": "39.541",
    "lon": "45.017"
  },
  "metadata": {},
  "source": {}
}