{
  "id": "AZ302037",
  "level": 2,
  "level_name": {
    "local": "Yaşayış məntəqəsi",
    "en": "Settlement"
  },
  "name": {
    "local": "Çarxı",
    "en": "Charkhi",
    "slug": "charkhi"
  },
  "code": {
    "id": "AZ302037",
    "iso": null
  },
  "parent": {
    "id": "AZ302",
    "level": 1,
    "name": {
      "local": "Xaçmaz",
      "en": "Khachmaz",
      "slug": "khachmaz"
    }
  },
  "ancestors": [
    {
      "id": "AZ302",
      "level": 1,
      "name": {
        "local": "Xaçmaz",
        "en": "Khachmaz",
        "slug": "khachmaz"
      }
    }
  ],
  "children_count": {},
  "zip_codes": [],
  "geo": {
    "lat": "41.392",
    "lon": "48.869"
  },
  "metadata": {},
  "source": {}
}